openeo_fastapi/__init__.py
openeo_fastapi/api/__init__.py
openeo_fastapi/api/app.py
openeo_fastapi/api/models.py
openeo_fastapi/api/types.py
openeo_fastapi/cli.py
openeo_fastapi/client/__init__.py
openeo_fastapi/client/auth.py
openeo_fastapi/client/collections.py
openeo_fastapi/client/core.py
openeo_fastapi/client/files.py
openeo_fastapi/client/jobs.py
openeo_fastapi/client/processes.py
openeo_fastapi/client/psql/__init__.py
openeo_fastapi/client/psql/engine.py
openeo_fastapi/client/psql/models.py
openeo_fastapi/client/psql/settings.py
openeo_fastapi/client/register.py
openeo_fastapi/client/settings.py
openeo_fastapi/templates.py
openeo_fastapi-2025.5.1.dist-info/LICENSE
openeo_fastapi-2025.5.1.dist-info/METADATA
openeo_fastapi-2025.5.1.dist-info/WHEEL
openeo_fastapi-2025.5.1.dist-info/entry_points.txt
openeo_fastapi-2025.5.1.dist-info/RECORD
