Metadata-Version: 2.1
Name: openeo-fastapi
Version: 2025.5.1
Summary: FastApi implementation conforming to the OpenEO Api specification.
Author: Sean Hoyal
Author-email: sean.hoyal@external.eodc.eu
Requires-Python: >=3.10,<3.12
Classifier: Development Status :: 4 - Beta
Classifier: Intended Audience :: Developers
Classifier: Programming Language :: Python
Classifier: Programming Language :: Python :: 3
Classifier: Programming Language :: Python :: 3.10
Classifier: Programming Language :: Python :: 3.11
Classifier: Programming Language :: Python :: 3 :: Only
Classifier: Programming Language :: Python :: 3.9
Requires-Dist: SQLAlchemy (>=2.0.27,<3.0.0)
Requires-Dist: aiohttp (>3.9)
Requires-Dist: alembic (>=1.13.1,<2.0.0)
Requires-Dist: attrs (>=23.1.0,<24.0.0)
Requires-Dist: click (==8.1.7)
Requires-Dist: fastapi (>=0.95.1,<0.96.0)
Requires-Dist: fsspec (>=2024.3.1,<2025.0.0)
Requires-Dist: httpx (>=0.27.0,<0.28.0)
Requires-Dist: joblib (>=1.3.2)
Requires-Dist: openeo-pg-parser-networkx (>=2024.1.1)
Requires-Dist: openeo-processes-dask (>=2025.5.1)
Requires-Dist: pip (>=23.3.2,<24.0.0)
Requires-Dist: psycopg2-binary (>=2.9.5,<3.0.0)
Requires-Dist: pydantic (<2)
Requires-Dist: pystac-client (>=0.7.5)
Requires-Dist: python-jose (>=3.3.0,<4.0.0)
Requires-Dist: requests (>=2.31.0,<3.0.0)
Requires-Dist: uvicorn (>=0.29.0,<0.30.0)
